Workbook
Name alpha0: Sheet1!$D$8
Name alpha1: Sheet1!$E$8
Name beta0: Sheet1!$D$9
Name beta1: Sheet1!$E$9
Name capital0: Sheet1!$D$10
Name capital1: Sheet1!$E$10
Name firmno0: Sheet1!$D$12
Name firmno1: Sheet1!$E$12
Name goodz0: Sheet1!$D$18
Name goodz1: Sheet1!$E$18
Name hhno0: Sheet1!$D$6
Name hhno1: Sheet1!$E$6
Name income0: Sheet1!$D$5
Name income1: Sheet1!$E$5
Name price0: Sheet1!$D$15
Name price1: Sheet1!$E$15
Name pricez: Sheet1!$D$13
Name pricez0: Sheet1!$D$13
Name pricez1: Sheet1!$E$13
Name qdd0: Sheet1!$D$17
Name qdemand0: Sheet1!$D$17
Name qdemand1: Sheet1!$E$17
Name Quantity0: Sheet1!$D$16
Name Quantity1: Sheet1!$E$16
Name rent0: Sheet1!$D$11
Name rent1: Sheet1!$E$11
Name theta: Sheet1!$D$4
Name theta0: Sheet1!$D$4
Name theta1: Sheet1!$E$4
Name utility0: Sheet1!$D$19
Name utility1: Sheet1!$E$19
Name wage0: Sheet1!$D$7
Name wage1: Sheet1!$E$7

Sheet Sheet1
G2: UTILITY
D3: Before | E3: After | G3: q | H3: zu0 | I3: zu1 | J3: zb0 | K3: zb1 | L3: q0 | M3: z0 | N3: z0 | O3: q0 | P3: q1 | Q3: z1 | R3: z1 | S3: q1 | T3: p | U3: q0 | V3: q1 | W3: Q0 | X3: Q1 | Y3: p0 | Z3: Q0 | AA3: p1 | AB3: Q1 | AC3: p | AD3: Q0 | AE3: Q1 | AF3: qs0 | AG3: qs1 | AH3: Qs0 | AI3: Qs1 | AJ3: C0 | AK3: C1 | AL3: ac0 | AM3: ac1 | AN3: TR0 | AO3: TR1 | AP3: Profit0 | AQ3: Profit1 | AR3: p | AS3: qs0 | AT3: qs1 | AU3: TR0 | AV3: TR1 | AW3: C0 | AX3: C1 | AY3: Profit0 | AZ3: Profit1 | BA3: ac0 | BB3: ac1 | BC3: p0 | BD3: p1
B4: Preference parameter | C4: q | D4: 0.5 | E4: =Diagram!O5 -> 0.5 | G4: 0.01 | H4: =(utility0/(G4^theta0))^(1/(1-theta0)) -> 12559.432 | I4: =(utility1/(G4^theta1))^(1/(1-theta1)) -> 12559.432 | J4: =(income0/pricez0)-(price0/pricez0)*G4 -> 49.950237 | K4: =(income1/pricez1)-(price1/pricez1)*G4 -> 49.950237 | L4: =qdd0 -> 5.0237729 | M4: 100 | N4: =goodz0 -> 25 | O4: 100 | P4: =qdemand1 -> 5.0237729 | Q4: 100 | R4: =goodz1 -> 25 | S4: 100 | T4: 0.01 | U4: =theta0*income0/T4 -> 2500 | V4: =theta1*income1/T4 -> 2500 | W4: =U4*hhno0 -> 250000 | X4: =V4*hhno1 -> 250000 | Y4: =price0 -> 4.9763396 | Z4: 0 | AA4: =price1 -> 4.9763396 | AB4: 0 | AC4: 0 | AD4: =Quantity0 -> 502.37729 | AE4: =Quantity1 -> 502.37729 | AF4: =(beta0*T4*(capital0^(alpha0/beta0))/wage0)^(beta0/(1-beta0)) -> 0.08 | AG4: =(beta1*T4*(capital1^(alpha1/beta1))/wage1)^(beta1/(1-beta1)) -> 0.08 | AH4: =AF4*firmno0 -> 8 | AI4: =AG4*firmno1 -> 8 | AJ4: =rent0*capital0+wage0*((AF4/(capital0^alpha0))^(1/beta0)) -> 10.00032 | AK4: =rent1*capital1+wage1*((AG4/(capital1^alpha1))^(1/beta1)) -> 10.00032 | AL4: =AJ4/AF4 -> 125.004 | AM4: =AK4/AG4 -> 125.004 | AN4: =price0*AF4 -> 0.39810717 | AO4: =price1*AG4 -> 0.39810717 | AP4: =AN4-AJ4 -> -9.6022128 | AQ4: =AO4-AK4 -> -9.6022128 | AR4: 0 | AS4: =Quantity0/firmno0 -> 5.0237729 | AT4: =Quantity1/firmno1 -> 5.0237729 | AU4: =price0*AS4 -> 25 | AV4: =price1*AT4 -> 25 | AW4: =rent0*capital0+wage0*((AS4/(capital0^alpha0))^(1/beta0)) -> 20 | AX4: =rent1*capital1+wage1*((AT4/(capital1^alpha1))^(1/beta1)) -> 20 | AY4: =AU4-AW4 -> 5 | AZ4: =AV4-AX4 -> 5 | BA4: =AW4/AS4 -> 3.9810717 | BB4: =AX4/AT4 -> 3.9810717 | BC4: =Y4 -> 4.9763396 | BD4: =AA4 -> 4.9763396
B5: Income | C5: y | D5: 50 | E5: =Diagram!O6 -> 50 | G5: 0.05 | H5: =(utility0/(G5^theta0))^(1/(1-theta0)) -> 2511.8864 | I5: =(utility1/(G5^theta1))^(1/(1-theta1)) -> 2511.8864 | J5: =(income0/pricez0)-(price0/pricez0)*G5 -> 49.751183 | K5: =(income1/pricez1)-(price1/pricez1)*G5 -> 49.751183 | L5: =L4 -> 5.0237729 | M5: 0 | N5: =N4 -> 25 | O5: 0 | P5: =P4 -> 5.0237729 | Q5: 0 | R5: =R4 -> 25 | S5: 0 | T5: 0.05 | U5: =theta0*income0/T5 -> 500 | V5: =theta1*income1/T5 -> 500 | W5: =U5*hhno0 -> 50000 | X5: =V5*hhno1 -> 50000 | Y5: =Y4 -> 4.9763396 | Z5: 1000 | AA5: =AA4 -> 4.9763396 | AB5: 1000 | AC5: 100 | AD5: =AD4 -> 502.37729 | AE5: =AE4 -> 502.37729 | AF5: =(beta0*T5*(capital0^(alpha0/beta0))/wage0)^(beta0/(1-beta0)) -> 0.23392142 | AG5: =(beta1*T5*(capital1^(alpha1/beta1))/wage1)^(beta1/(1-beta1)) -> 0.23392142 | AH5: =AF5*firmno0 -> 23.392142 | AI5: =AG5*firmno1 -> 23.392142 | AJ5: =rent0*capital0+wage0*((AF5/(capital0^alpha0))^(1/beta0)) -> 10.004678 | AK5: =rent1*capital1+wage1*((AG5/(capital1^alpha1))^(1/beta1)) -> 10.004678 | AL5: =AJ5/AF5 -> 42.769399 | AM5: =AK5/AG5 -> 42.769399 | AN5: =price0*AF5 -> 1.1640724 | AO5: =price1*AG5 -> 1.1640724 | AP5: =AN5-AJ5 -> -8.840606 | AQ5: =AO5-AK5 -> -8.840606 | AR5: 100 | AS5: =AS4 -> 5.0237729 | AT5: =AT4 -> 5.0237729
B6: Number of households | C6: H | D6: 100 | E6: =Diagram!O7 -> 100 | G6: 0.1 | H6: =(utility0/(G6^theta0))^(1/(1-theta0)) -> 1255.9432 | I6: =(utility1/(G6^theta1))^(1/(1-theta1)) -> 1255.9432 | J6: =(income0/pricez0)-(price0/pricez0)*G6 -> 49.502366 | K6: =(income1/pricez1)-(price1/pricez1)*G6 -> 49.502366 | T6: 0.1 | U6: =theta0*income0/T6 -> 250 | V6: =theta1*income1/T6 -> 250 | W6: =U6*hhno0 -> 25000 | X6: =V6*hhno1 -> 25000 | AF6: =(beta0*T6*(capital0^(alpha0/beta0))/wage0)^(beta0/(1-beta0)) -> 0.37132711 | AG6: =(beta1*T6*(capital1^(alpha1/beta1))/wage1)^(beta1/(1-beta1)) -> 0.37132711 | AH6: =AF6*firmno0 -> 37.132711 | AI6: =AG6*firmno1 -> 37.132711 | AJ6: =rent0*capital0+wage0*((AF6/(capital0^alpha0))^(1/beta0)) -> 10.014853 | AK6: =rent1*capital1+wage1*((AG6/(capital1^alpha1))^(1/beta1)) -> 10.014853 | AL6: =AJ6/AF6 -> 26.970434 | AM6: =AK6/AG6 -> 26.970434 | AN6: =price0*AF6 -> 1.8478498 | AO6: =price1*AG6 -> 1.8478498 | AP6: =AN6-AJ6 -> -8.1670033 | AQ6: =AO6-AK6 -> -8.1670033
B7: Wage | C7: w | D7: 0.5 | E7: =Diagram!O8 -> 0.5 | G7: 0.5 | H7: =(utility0/(G7^theta0))^(1/(1-theta0)) -> 251.18864 | I7: =(utility1/(G7^theta1))^(1/(1-theta1)) -> 251.18864 | J7: =(income0/pricez0)-(price0/pricez0)*G7 -> 47.51183 | K7: =(income1/pricez1)-(price1/pricez1)*G7 -> 47.51183 | T7: 0.5 | U7: =theta0*income0/T7 -> 50 | V7: =theta1*income1/T7 -> 50 | W7: =U7*hhno0 -> 5000 | X7: =V7*hhno1 -> 5000 | AF7: =(beta0*T7*(capital0^(alpha0/beta0))/wage0)^(beta0/(1-beta0)) -> 1.085767 | AG7: =(beta1*T7*(capital1^(alpha1/beta1))/wage1)^(beta1/(1-beta1)) -> 1.085767 | AH7: =AF7*firmno0 -> 108.5767 | AI7: =AG7*firmno1 -> 108.5767 | AJ7: =rent0*capital0+wage0*((AF7/(capital0^alpha0))^(1/beta0)) -> 10.217153 | AK7: =rent1*capital1+wage1*((AG7/(capital1^alpha1))^(1/beta1)) -> 10.217153 | AL7: =AJ7/AF7 -> 9.4100787 | AM7: =AK7/AG7 -> 9.4100787 | AN7: =price0*AF7 -> 5.4031456 | AO7: =price1*AG7 -> 5.4031456 | AP7: =AN7-AJ7 -> -4.8140078 | AQ7: =AO7-AK7 -> -4.8140078
B8: Production parameter | C8: α | D8: 0.6 | E8: =Diagram!O9 -> 0.6 | G8: 1 | H8: =(utility0/(G8^theta0))^(1/(1-theta0)) -> 125.59432 | I8: =(utility1/(G8^theta1))^(1/(1-theta1)) -> 125.59432 | J8: =(income0/pricez0)-(price0/pricez0)*G8 -> 45.02366 | K8: =(income1/pricez1)-(price1/pricez1)*G8 -> 45.02366 | T8: 1 | U8: =theta0*income0/T8 -> 25 | V8: =theta1*income1/T8 -> 25 | W8: =U8*hhno0 -> 2500 | X8: =V8*hhno1 -> 2500 | AF8: =(beta0*T8*(capital0^(alpha0/beta0))/wage0)^(beta0/(1-beta0)) -> 1.7235478 | AG8: =(beta1*T8*(capital1^(alpha1/beta1))/wage1)^(beta1/(1-beta1)) -> 1.7235478 | AH8: =AF8*firmno0 -> 172.35478 | AI8: =AG8*firmno1 -> 172.35478 | AJ8: =rent0*capital0+wage0*((AF8/(capital0^alpha0))^(1/beta0)) -> 10.689419 | AK8: =rent1*capital1+wage1*((AG8/(capital1^alpha1))^(1/beta1)) -> 10.689419 | AL8: =AJ8/AF8 -> 6.201986 | AM8: =AK8/AG8 -> 6.201986 | AN8: =price0*AF8 -> 8.576959 | AO8: =price1*AG8 -> 8.576959 | AP8: =AN8-AJ8 -> -2.1124601 | AQ8: =AO8-AK8 -> -2.1124601
B9: Production parameter | C9: β | D9: 0.4 | E9: =Diagram!O10 -> 0.4 | G9: 1.5 | H9: =(utility0/(G9^theta0))^(1/(1-theta0)) -> 83.729548 | I9: =(utility1/(G9^theta1))^(1/(1-theta1)) -> 83.729548 | J9: =(income0/pricez0)-(price0/pricez0)*G9 -> 42.535491 | K9: =(income1/pricez1)-(price1/pricez1)*G9 -> 42.535491 | T9: 1.5 | U9: =theta0*income0/T9 -> 16.666667 | V9: =theta1*income1/T9 -> 16.666667 | W9: =U9*hhno0 -> 1666.6667 | X9: =V9*hhno1 -> 1666.6667 | AF9: =(beta0*T9*(capital0^(alpha0/beta0))/wage0)^(beta0/(1-beta0)) -> 2.2584865 | AG9: =(beta1*T9*(capital1^(alpha1/beta1))/wage1)^(beta1/(1-beta1)) -> 2.2584865 | AH9: =AF9*firmno0 -> 225.84865 | AI9: =AG9*firmno1 -> 225.84865 | AJ9: =rent0*capital0+wage0*((AF9/(capital0^alpha0))^(1/beta0)) -> 11.355092 | AK9: =rent1*capital1+wage1*((AG9/(capital1^alpha1))^(1/beta1)) -> 11.355092 | AL9: =AJ9/AF9 -> 5.027744 | AM9: =AK9/AG9 -> 5.027744 | AN9: =price0*AF9 -> 11.238996 | AO9: =price1*AG9 -> 11.238996 | AP9: =AN9-AJ9 -> -0.11609616 | AQ9: =AO9-AK9 -> -0.11609616
B10: Capital | C10: K | D10: 2 | E10: =Diagram!O11 -> 2 | G10: 2 | H10: =(utility0/(G10^theta0))^(1/(1-theta0)) -> 62.797161 | I10: =(utility1/(G10^theta1))^(1/(1-theta1)) -> 62.797161 | J10: =(income0/pricez0)-(price0/pricez0)*G10 -> 40.047321 | K10: =(income1/pricez1)-(price1/pricez1)*G10 -> 40.047321 | T10: 2 | U10: =theta0*income0/T10 -> 12.5 | V10: =theta1*income1/T10 -> 12.5 | W10: =U10*hhno0 -> 1250 | X10: =V10*hhno1 -> 1250 | AF10: =(beta0*T10*(capital0^(alpha0/beta0))/wage0)^(beta0/(1-beta0)) -> 2.7359615 | AG10: =(beta1*T10*(capital1^(alpha1/beta1))/wage1)^(beta1/(1-beta1)) -> 2.7359615 | AH10: =AF10*firmno0 -> 273.59615 | AI10: =AG10*firmno1 -> 273.59615 | AJ10: =rent0*capital0+wage0*((AF10/(capital0^alpha0))^(1/beta0)) -> 12.188769 | AK10: =rent1*capital1+wage1*((AG10/(capital1^alpha1))^(1/beta1)) -> 12.188769 | AL10: =AJ10/AF10 -> 4.4550222 | AM10: =AK10/AG10 -> 4.4550222 | AN10: =price0*AF10 -> 13.615074 | AO10: =price1*AG10 -> 13.615074 | AP10: =AN10-AJ10 -> 1.4263045 | AQ10: =AO10-AK10 -> 1.4263045
B11: Rental of capital | C11: r | D11: 5 | E11: =Diagram!O12 -> 5 | G11: 2.5 | H11: =(utility0/(G11^theta0))^(1/(1-theta0)) -> 50.237729 | I11: =(utility1/(G11^theta1))^(1/(1-theta1)) -> 50.237729 | J11: =(income0/pricez0)-(price0/pricez0)*G11 -> 37.559151 | K11: =(income1/pricez1)-(price1/pricez1)*G11 -> 37.559151 | T11: 2.5 | U11: =theta0*income0/T11 -> 10 | V11: =theta1*income1/T11 -> 10 | W11: =U11*hhno0 -> 1000 | X11: =V11*hhno1 -> 1000 | AF11: =(beta0*T11*(capital0^(alpha0/beta0))/wage0)^(beta0/(1-beta0)) -> 3.1748021 | AG11: =(beta1*T11*(capital1^(alpha1/beta1))/wage1)^(beta1/(1-beta1)) -> 3.1748021 | AH11: =AF11*firmno0 -> 317.48021 | AI11: =AG11*firmno1 -> 317.48021 | AJ11: =rent0*capital0+wage0*((AF11/(capital0^alpha0))^(1/beta0)) -> 13.174802 | AK11: =rent1*capital1+wage1*((AG11/(capital1^alpha1))^(1/beta1)) -> 13.174802 | AL11: =AJ11/AF11 -> 4.1498026 | AM11: =AK11/AG11 -> 4.1498026 | AN11: =price0*AF11 -> 15.798894 | AO11: =price1*AG11 -> 15.798894 | AP11: =AN11-AJ11 -> 2.6240914 | AQ11: =AO11-AK11 -> 2.6240914
B12: Number of firms | C12: N | D12: 100 | E12: =Diagram!O13 -> 100 | G12: 3 | H12: =(utility0/(G12^theta0))^(1/(1-theta0)) -> 41.864774 | I12: =(utility1/(G12^theta1))^(1/(1-theta1)) -> 41.864774 | J12: =(income0/pricez0)-(price0/pricez0)*G12 -> 35.070981 | K12: =(income1/pricez1)-(price1/pricez1)*G12 -> 35.070981 | T12: 3 | U12: =theta0*income0/T12 -> 8.3333333 | V12: =theta1*income1/T12 -> 8.3333333 | W12: =U12*hhno0 -> 833.33333 | X12: =V12*hhno1 -> 833.33333 | AF12: =(beta0*T12*(capital0^(alpha0/beta0))/wage0)^(beta0/(1-beta0)) -> 3.5851238 | AG12: =(beta1*T12*(capital1^(alpha1/beta1))/wage1)^(beta1/(1-beta1)) -> 3.5851238 | AH12: =AF12*firmno0 -> 358.51238 | AI12: =AG12*firmno1 -> 358.51238 | AJ12: =rent0*capital0+wage0*((AF12/(capital0^alpha0))^(1/beta0)) -> 14.302149 | AK12: =rent1*capital1+wage1*((AG12/(capital1^alpha1))^(1/beta1)) -> 14.302149 | AL12: =AJ12/AF12 -> 3.989304 | AM12: =AK12/AG12 -> 3.989304 | AN12: =price0*AF12 -> 17.840794 | AO12: =price1*AG12 -> 17.840794 | AP12: =AN12-AJ12 -> 3.5386451 | AQ12: =AO12-AK12 -> 3.5386451
B13: Price of other good | C13: Pz | D13: 1 | E13: =pricez -> 1 | G13: 3.5 | H13: =(utility0/(G13^theta0))^(1/(1-theta0)) -> 35.884092 | I13: =(utility1/(G13^theta1))^(1/(1-theta1)) -> 35.884092 | J13: =(income0/pricez0)-(price0/pricez0)*G13 -> 32.582811 | K13: =(income1/pricez1)-(price1/pricez1)*G13 -> 32.582811 | T13: 3.5 | U13: =theta0*income0/T13 -> 7.1428571 | V13: =theta1*income1/T13 -> 7.1428571 | W13: =U13*hhno0 -> 714.28571 | X13: =V13*hhno1 -> 714.28571 | AF13: =(beta0*T13*(capital0^(alpha0/beta0))/wage0)^(beta0/(1-beta0)) -> 3.9731536 | AG13: =(beta1*T13*(capital1^(alpha1/beta1))/wage1)^(beta1/(1-beta1)) -> 3.9731536 | AH13: =AF13*firmno0 -> 397.31536 | AI13: =AG13*firmno1 -> 397.31536 | AJ13: =rent0*capital0+wage0*((AF13/(capital0^alpha0))^(1/beta0)) -> 15.562415 | AK13: =rent1*capital1+wage1*((AG13/(capital1^alpha1))^(1/beta1)) -> 15.562415 | AL13: =AJ13/AF13 -> 3.9168924 | AM13: =AK13/AG13 -> 3.9168924 | AN13: =price0*AF13 -> 19.771761 | AO13: =price1*AG13 -> 19.771761 | AP13: =AN13-AJ13 -> 4.2093465 | AQ13: =AO13-AK13 -> 4.2093465
G14: 4 | H14: =(utility0/(G14^theta0))^(1/(1-theta0)) -> 31.39858 | I14: =(utility1/(G14^theta1))^(1/(1-theta1)) -> 31.39858 | J14: =(income0/pricez0)-(price0/pricez0)*G14 -> 30.094641 | K14: =(income1/pricez1)-(price1/pricez1)*G14 -> 30.094641 | T14: 4 | U14: =theta0*income0/T14 -> 6.25 | V14: =theta1*income1/T14 -> 6.25 | W14: =U14*hhno0 -> 625 | X14: =V14*hhno1 -> 625 | AF14: =(beta0*T14*(capital0^(alpha0/beta0))/wage0)^(beta0/(1-beta0)) -> 4.3430682 | AG14: =(beta1*T14*(capital1^(alpha1/beta1))/wage1)^(beta1/(1-beta1)) -> 4.3430682 | AH14: =AF14*firmno0 -> 434.30682 | AI14: =AG14*firmno1 -> 434.30682 | AJ14: =rent0*capital0+wage0*((AF14/(capital0^alpha0))^(1/beta0)) -> 16.948909 | AK14: =rent1*capital1+wage1*((AG14/(capital1^alpha1))^(1/beta1)) -> 16.948909 | AL14: =AJ14/AF14 -> 3.9025197 | AM14: =AK14/AG14 -> 3.9025197 | AN14: =price0*AF14 -> 21.612582 | AO14: =price1*AG14 -> 21.612582 | AP14: =AN14-AJ14 -> 4.6636732 | AQ14: =AO14-AK14 -> 4.6636732
B15: Price equilibrium | C15: P | D15: =(((hhno0*theta0*income0)/firmno0)^(1-beta0))*((wage0/(beta0*(capital0^(alpha0/beta0))))^beta0) -> 4.9763396 | E15: =(((hhno1*theta1*income1)/firmno1)^(1-beta1))*((wage1/(beta1*(capital1^(alpha1/beta1))))^beta1) -> 4.9763396 | G15: 4.5 | H15: =(utility0/(G15^theta0))^(1/(1-theta0)) -> 27.909849 | I15: =(utility1/(G15^theta1))^(1/(1-theta1)) -> 27.909849 | J15: =(income0/pricez0)-(price0/pricez0)*G15 -> 27.606472 | K15: =(income1/pricez1)-(price1/pricez1)*G15 -> 27.606472 | T15: 4.5 | U15: =theta0*income0/T15 -> 5.5555556 | V15: =theta1*income1/T15 -> 5.5555556 | W15: =U15*hhno0 -> 555.55556 | X15: =V15*hhno1 -> 555.55556 | AF15: =(beta0*T15*(capital0^(alpha0/beta0))/wage0)^(beta0/(1-beta0)) -> 4.6978412 | AG15: =(beta1*T15*(capital1^(alpha1/beta1))/wage1)^(beta1/(1-beta1)) -> 4.6978412 | AH15: =AF15*firmno0 -> 469.78412 | AI15: =AG15*firmno1 -> 469.78412 | AJ15: =rent0*capital0+wage0*((AF15/(capital0^alpha0))^(1/beta0)) -> 18.456114 | AK15: =rent1*capital1+wage1*((AG15/(capital1^alpha1))^(1/beta1)) -> 18.456114 | AL15: =AJ15/AF15 -> 3.9286373 | AM15: =AK15/AG15 -> 3.9286373 | AN15: =price0*AF15 -> 23.378053 | AO15: =price1*AG15 -> 23.378053 | AP15: =AN15-AJ15 -> 4.9219391 | AQ15: =AO15-AK15 -> 4.9219391
B16: Quantity equilibrium | C16: Q | D16: =hhno0*theta0*income0/price0 -> 502.37729 | E16: =hhno1*theta1*income1/price1 -> 502.37729 | G16: 5 | H16: =(utility0/(G16^theta0))^(1/(1-theta0)) -> 25.118864 | I16: =(utility1/(G16^theta1))^(1/(1-theta1)) -> 25.118864 | J16: =(income0/pricez0)-(price0/pricez0)*G16 -> 25.118302 | K16: =(income1/pricez1)-(price1/pricez1)*G16 -> 25.118302 | T16: 5 | U16: =theta0*income0/T16 -> 5 | V16: =theta1*income1/T16 -> 5 | W16: =U16*hhno0 -> 500 | X16: =V16*hhno1 -> 500 | AF16: =(beta0*T16*(capital0^(alpha0/beta0))/wage0)^(beta0/(1-beta0)) -> 5.0396842 | AG16: =(beta1*T16*(capital1^(alpha1/beta1))/wage1)^(beta1/(1-beta1)) -> 5.0396842 | AH16: =AF16*firmno0 -> 503.96842 | AI16: =AG16*firmno1 -> 503.96842 | AJ16: =rent0*capital0+wage0*((AF16/(capital0^alpha0))^(1/beta0)) -> 20.079368 | AK16: =rent1*capital1+wage1*((AG16/(capital1^alpha1))^(1/beta1)) -> 20.079368 | AL16: =AJ16/AF16 -> 3.9842513 | AM16: =AK16/AG16 -> 3.9842513 | AN16: =price0*AF16 -> 25.07918 | AO16: =price1*AG16 -> 25.07918 | AP16: =AN16-AJ16 -> 4.9998118 | AQ16: =AO16-AK16 -> 4.9998118
B17: Individual demand | C17: q | D17: =Quantity0/hhno0 -> 5.0237729 | E17: =Quantity1/hhno1 -> 5.0237729 | G17: 5.5 | H17: =(utility0/(G17^theta0))^(1/(1-theta0)) -> 22.835331 | I17: =(utility1/(G17^theta1))^(1/(1-theta1)) -> 22.835331 | J17: =(income0/pricez0)-(price0/pricez0)*G17 -> 22.630132 | K17: =(income1/pricez1)-(price1/pricez1)*G17 -> 22.630132 | T17: 5.5 | U17: =theta0*income0/T17 -> 4.5454545 | V17: =theta1*income1/T17 -> 4.5454545 | W17: =U17*hhno0 -> 454.54545 | X17: =V17*hhno1 -> 454.54545 | AF17: =(beta0*T17*(capital0^(alpha0/beta0))/wage0)^(beta0/(1-beta0)) -> 5.3702988 | AG17: =(beta1*T17*(capital1^(alpha1/beta1))/wage1)^(beta1/(1-beta1)) -> 5.3702988 | AH17: =AF17*firmno0 -> 537.02988 | AI17: =AG17*firmno1 -> 537.02988 | AJ17: =rent0*capital0+wage0*((AF17/(capital0^alpha0))^(1/beta0)) -> 21.814657 | AK17: =rent1*capital1+wage1*((AG17/(capital1^alpha1))^(1/beta1)) -> 21.814657 | AL17: =AJ17/AF17 -> 4.0620938 | AM17: =AK17/AG17 -> 4.0620938 | AN17: =price0*AF17 -> 26.724431 | AO17: =price1*AG17 -> 26.724431 | AP17: =AN17-AJ17 -> 4.9097733 | AQ17: =AO17-AK17 -> 4.9097733
B18: Individual demand for z | C18: z | D18: =(1-theta0)*income0/pricez0 -> 25 | E18: =(1-theta1)*income1/pricez1 -> 25 | G18: 6 | H18: =(utility0/(G18^theta0))^(1/(1-theta0)) -> 20.932387 | I18: =(utility1/(G18^theta1))^(1/(1-theta1)) -> 20.932387 | J18: =(income0/pricez0)-(price0/pricez0)*G18 -> 20.141962 | K18: =(income1/pricez1)-(price1/pricez1)*G18 -> 20.141962 | T18: 6 | U18: =theta0*income0/T18 -> 4.1666667 | V18: =theta1*income1/T18 -> 4.1666667 | W18: =U18*hhno0 -> 416.66667 | X18: =V18*hhno1 -> 416.66667 | AF18: =(beta0*T18*(capital0^(alpha0/beta0))/wage0)^(beta0/(1-beta0)) -> 5.6910293 | AG18: =(beta1*T18*(capital1^(alpha1/beta1))/wage1)^(beta1/(1-beta1)) -> 5.6910293 | AH18: =AF18*firmno0 -> 569.10293 | AI18: =AG18*firmno1 -> 569.10293 | AJ18: =rent0*capital0+wage0*((AF18/(capital0^alpha0))^(1/beta0)) -> 23.65847 | AK18: =rent1*capital1+wage1*((AG18/(capital1^alpha1))^(1/beta1)) -> 23.65847 | AL18: =AJ18/AF18 -> 4.1571514 | AM18: =AK18/AG18 -> 4.1571514 | AN18: =price0*AF18 -> 28.320495 | AO18: =price1*AG18 -> 28.320495 | AP18: =AN18-AJ18 -> 4.6620243 | AQ18: =AO18-AK18 -> 4.6620243
B19: Utility | C19: u | D19: =(qdemand0^theta0)*(goodz0^(1-theta0)) -> 11.206887 | E19: =(qdemand1^theta1)*(goodz1^(1-theta1)) -> 11.206887 | G19: 6.5 | H19: =(utility0/(G19^theta0))^(1/(1-theta0)) -> 19.322203 | I19: =(utility1/(G19^theta1))^(1/(1-theta1)) -> 19.322203 | J19: =(income0/pricez0)-(price0/pricez0)*G19 -> 17.653792 | K19: =(income1/pricez1)-(price1/pricez1)*G19 -> 17.653792 | T19: 6.5 | U19: =theta0*income0/T19 -> 3.8461538 | V19: =theta1*income1/T19 -> 3.8461538 | W19: =U19*hhno0 -> 384.61538 | X19: =V19*hhno1 -> 384.61538 | AF19: =(beta0*T19*(capital0^(alpha0/beta0))/wage0)^(beta0/(1-beta0)) -> 6.0029615 | AG19: =(beta1*T19*(capital1^(alpha1/beta1))/wage1)^(beta1/(1-beta1)) -> 6.0029615 | AH19: =AF19*firmno0 -> 600.29615 | AI19: =AG19*firmno1 -> 600.29615 | AJ19: =rent0*capital0+wage0*((AF19/(capital0^alpha0))^(1/beta0)) -> 25.6077 | AK19: =rent1*capital1+wage1*((AG19/(capital1^alpha1))^(1/beta1)) -> 25.6077 | AL19: =AJ19/AF19 -> 4.2658444 | AM19: =AK19/AG19 -> 4.2658444 | AN19: =price0*AF19 -> 29.872775 | AO19: =price1*AG19 -> 29.872775 | AP19: =AN19-AJ19 -> 4.2650753 | AQ19: =AO19-AK19 -> 4.2650753
G20: 7 | H20: =(utility0/(G20^theta0))^(1/(1-theta0)) -> 17.942046 | I20: =(utility1/(G20^theta1))^(1/(1-theta1)) -> 17.942046 | J20: =(income0/pricez0)-(price0/pricez0)*G20 -> 15.165623 | K20: =(income1/pricez1)-(price1/pricez1)*G20 -> 15.165623 | T20: 7 | U20: =theta0*income0/T20 -> 3.5714286 | V20: =theta1*income1/T20 -> 3.5714286 | W20: =U20*hhno0 -> 357.14286 | X20: =V20*hhno1 -> 357.14286 | AF20: =(beta0*T20*(capital0^(alpha0/beta0))/wage0)^(beta0/(1-beta0)) -> 6.3069881 | AG20: =(beta1*T20*(capital1^(alpha1/beta1))/wage1)^(beta1/(1-beta1)) -> 6.3069881 | AH20: =AF20*firmno0 -> 630.69881 | AI20: =AG20*firmno1 -> 630.69881 | AJ20: =rent0*capital0+wage0*((AF20/(capital0^alpha0))^(1/beta0)) -> 27.659567 | AK20: =rent1*capital1+wage1*((AG20/(capital1^alpha1))^(1/beta1)) -> 27.659567 | AL20: =AJ20/AF20 -> 4.3855429 | AM20: =AK20/AG20 -> 4.3855429 | AN20: =price0*AF20 -> 31.385715 | AO20: =price1*AG20 -> 31.385715 | AP20: =AN20-AJ20 -> 3.7261482 | AQ20: =AO20-AK20 -> 3.7261482
G21: 7.5 | H21: =(utility0/(G21^theta0))^(1/(1-theta0)) -> 16.74591 | I21: =(utility1/(G21^theta1))^(1/(1-theta1)) -> 16.74591 | J21: =(income0/pricez0)-(price0/pricez0)*G21 -> 12.677453 | K21: =(income1/pricez1)-(price1/pricez1)*G21 -> 12.677453 | T21: 7.5 | U21: =theta0*income0/T21 -> 3.3333333 | V21: =theta1*income1/T21 -> 3.3333333 | W21: =U21*hhno0 -> 333.33333 | X21: =V21*hhno1 -> 333.33333 | AF21: =(beta0*T21*(capital0^(alpha0/beta0))/wage0)^(beta0/(1-beta0)) -> 6.6038545 | AG21: =(beta1*T21*(capital1^(alpha1/beta1))/wage1)^(beta1/(1-beta1)) -> 6.6038545 | AH21: =AF21*firmno0 -> 660.38545 | AI21: =AG21*firmno1 -> 660.38545 | AJ21: =rent0*capital0+wage0*((AF21/(capital0^alpha0))^(1/beta0)) -> 29.811563 | AK21: =rent1*capital1+wage1*((AG21/(capital1^alpha1))^(1/beta1)) -> 29.811563 | AL21: =AJ21/AF21 -> 4.5142672 | AM21: =AK21/AG21 -> 4.5142672 | AN21: =price0*AF21 -> 32.863023 | AO21: =price1*AG21 -> 32.863023 | AP21: =AN21-AJ21 -> 3.0514594 | AQ21: =AO21-AK21 -> 3.0514594
G22: 8 | H22: =(utility0/(G22^theta0))^(1/(1-theta0)) -> 15.69929 | I22: =(utility1/(G22^theta1))^(1/(1-theta1)) -> 15.69929 | J22: =(income0/pricez0)-(price0/pricez0)*G22 -> 10.189283 | K22: =(income1/pricez1)-(price1/pricez1)*G22 -> 10.189283 | T22: 8 | U22: =theta0*income0/T22 -> 3.125 | V22: =theta1*income1/T22 -> 3.125 | W22: =U22*hhno0 -> 312.5 | X22: =V22*hhno1 -> 312.5 | AF22: =(beta0*T22*(capital0^(alpha0/beta0))/wage0)^(beta0/(1-beta0)) -> 6.894191 | AG22: =(beta1*T22*(capital1^(alpha1/beta1))/wage1)^(beta1/(1-beta1)) -> 6.894191 | AH22: =AF22*firmno0 -> 689.4191 | AI22: =AG22*firmno1 -> 689.4191 | AJ22: =rent0*capital0+wage0*((AF22/(capital0^alpha0))^(1/beta0)) -> 32.061411 | AK22: =rent1*capital1+wage1*((AG22/(capital1^alpha1))^(1/beta1)) -> 32.061411 | AL22: =AJ22/AF22 -> 4.6504965 | AM22: =AK22/AG22 -> 4.6504965 | AN22: =price0*AF22 -> 34.307836 | AO22: =price1*AG22 -> 34.307836 | AP22: =AN22-AJ22 -> 2.2464247 | AQ22: =AO22-AK22 -> 2.2464247
G23: 8.5 | H23: =(utility0/(G23^theta0))^(1/(1-theta0)) -> 14.775803 | I23: =(utility1/(G23^theta1))^(1/(1-theta1)) -> 14.775803 | J23: =(income0/pricez0)-(price0/pricez0)*G23 -> 7.7011131 | K23: =(income1/pricez1)-(price1/pricez1)*G23 -> 7.7011131 | T23: 8.5 | U23: =theta0*income0/T23 -> 2.9411765 | V23: =theta1*income1/T23 -> 2.9411765 | W23: =U23*hhno0 -> 294.11765 | X23: =V23*hhno1 -> 294.11765 | AF23: =(beta0*T23*(capital0^(alpha0/beta0))/wage0)^(beta0/(1-beta0)) -> 7.1785369 | AG23: =(beta1*T23*(capital1^(alpha1/beta1))/wage1)^(beta1/(1-beta1)) -> 7.1785369 | AH23: =AF23*firmno0 -> 717.85369 | AI23: =AG23*firmno1 -> 717.85369 | AJ23: =rent0*capital0+wage0*((AF23/(capital0^alpha0))^(1/beta0)) -> 34.407025 | AK23: =rent1*capital1+wage1*((AG23/(capital1^alpha1))^(1/beta1)) -> 34.407025 | AL23: =AJ23/AF23 -> 4.7930415 | AM23: =AK23/AG23 -> 4.7930415 | AN23: =price0*AF23 -> 35.722838 | AO23: =price1*AG23 -> 35.722838 | AP23: =AN23-AJ23 -> 1.3158122 | AQ23: =AO23-AK23 -> 1.3158122
G24: 9 | H24: =(utility0/(G24^theta0))^(1/(1-theta0)) -> 13.954925 | I24: =(utility1/(G24^theta1))^(1/(1-theta1)) -> 13.954925 | J24: =(income0/pricez0)-(price0/pricez0)*G24 -> 5.2129433 | K24: =(income1/pricez1)-(price1/pricez1)*G24 -> 5.2129433 | T24: 9 | U24: =theta0*income0/T24 -> 2.7777778 | V24: =theta1*income1/T24 -> 2.7777778 | W24: =U24*hhno0 -> 277.77778 | X24: =V24*hhno1 -> 277.77778 | AF24: =(beta0*T24*(capital0^(alpha0/beta0))/wage0)^(beta0/(1-beta0)) -> 7.457358 | AG24: =(beta1*T24*(capital1^(alpha1/beta1))/wage1)^(beta1/(1-beta1)) -> 7.457358 | AH24: =AF24*firmno0 -> 745.7358 | AI24: =AG24*firmno1 -> 745.7358 | AJ24: =rent0*capital0+wage0*((AF24/(capital0^alpha0))^(1/beta0)) -> 36.846489 | AK24: =rent1*capital1+wage1*((AG24/(capital1^alpha1))^(1/beta1)) -> 36.846489 | AL24: =AJ24/AF24 -> 4.9409575 | AM24: =AK24/AG24 -> 4.9409575 | AN24: =price0*AF24 -> 37.110346 | AO24: =price1*AG24 -> 37.110346 | AP24: =AN24-AJ24 -> 0.26385738 | AQ24: =AO24-AK24 -> 0.26385738
G25: 9.5 | H25: =(utility0/(G25^theta0))^(1/(1-theta0)) -> 13.220455 | I25: =(utility1/(G25^theta1))^(1/(1-theta1)) -> 13.220455 | J25: =(income0/pricez0)-(price0/pricez0)*G25 -> 2.7247735 | K25: =(income1/pricez1)-(price1/pricez1)*G25 -> 2.7247735 | T25: 9.5 | U25: =theta0*income0/T25 -> 2.6315789 | V25: =theta1*income1/T25 -> 2.6315789 | W25: =U25*hhno0 -> 263.15789 | X25: =V25*hhno1 -> 263.15789 | AF25: =(beta0*T25*(capital0^(alpha0/beta0))/wage0)^(beta0/(1-beta0)) -> 7.7310602 | AG25: =(beta1*T25*(capital1^(alpha1/beta1))/wage1)^(beta1/(1-beta1)) -> 7.7310602 | AH25: =AF25*firmno0 -> 773.10602 | AI25: =AG25*firmno1 -> 773.10602 | AJ25: =rent0*capital0+wage0*((AF25/(capital0^alpha0))^(1/beta0)) -> 39.378029 | AK25: =rent1*capital1+wage1*((AG25/(capital1^alpha1))^(1/beta1)) -> 39.378029 | AL25: =AJ25/AF25 -> 5.0934836 | AM25: =AK25/AG25 -> 5.0934836 | AN25: =price0*AF25 -> 38.472381 | AO25: =price1*AG25 -> 38.472381 | AP25: =AN25-AJ25 -> -0.90564744 | AQ25: =AO25-AK25 -> -0.90564744
G26: 10 | H26: =(utility0/(G26^theta0))^(1/(1-theta0)) -> 12.559432 | I26: =(utility1/(G26^theta1))^(1/(1-theta1)) -> 12.559432 | J26: =(income0/pricez0)-(price0/pricez0)*G26 -> 0.23660368 | K26: =(income1/pricez1)-(price1/pricez1)*G26 -> 0.23660368 | T26: 10 | U26: =theta0*income0/T26 -> 2.5 | V26: =theta1*income1/T26 -> 2.5 | W26: =U26*hhno0 -> 250 | X26: =V26*hhno1 -> 250 | AF26: =(beta0*T26*(capital0^(alpha0/beta0))/wage0)^(beta0/(1-beta0)) -> 8 | AG26: =(beta1*T26*(capital1^(alpha1/beta1))/wage1)^(beta1/(1-beta1)) -> 8 | AH26: =AF26*firmno0 -> 800 | AI26: =AG26*firmno1 -> 800 | AJ26: =rent0*capital0+wage0*((AF26/(capital0^alpha0))^(1/beta0)) -> 42 | AK26: =rent1*capital1+wage1*((AG26/(capital1^alpha1))^(1/beta1)) -> 42 | AL26: =AJ26/AF26 -> 5.25 | AM26: =AK26/AG26 -> 5.25 | AN26: =price0*AF26 -> 39.810717 | AO26: =price1*AG26 -> 39.810717 | AP26: =AN26-AJ26 -> -2.1892829 | AQ26: =AO26-AK26 -> -2.1892829
G27: 10.5 | H27: =(utility0/(G27^theta0))^(1/(1-theta0)) -> 11.961364 | I27: =(utility1/(G27^theta1))^(1/(1-theta1)) -> 11.961364 | J27: =(income0/pricez0)-(price0/pricez0)*G27 -> -2.2515661 | K27: =(income1/pricez1)-(price1/pricez1)*G27 -> -2.2515661 | T27: 10.5 | U27: =theta0*income0/T27 -> 2.3809524 | V27: =theta1*income1/T27 -> 2.3809524 | W27: =U27*hhno0 -> 238.09524 | X27: =V27*hhno1 -> 238.09524 | AF27: =(beta0*T27*(capital0^(alpha0/beta0))/wage0)^(beta0/(1-beta0)) -> 8.2644924 | AG27: =(beta1*T27*(capital1^(alpha1/beta1))/wage1)^(beta1/(1-beta1)) -> 8.2644924 | AH27: =AF27*firmno0 -> 826.44924 | AI27: =AG27*firmno1 -> 826.44924 | AJ27: =rent0*capital0+wage0*((AF27/(capital0^alpha0))^(1/beta0)) -> 44.710868 | AK27: =rent1*capital1+wage1*((AG27/(capital1^alpha1))^(1/beta1)) -> 44.710868 | AL27: =AJ27/AF27 -> 5.4099957 | AM27: =AK27/AG27 -> 5.4099957 | AN27: =price0*AF27 -> 41.126921 | AO27: =price1*AG27 -> 41.126921 | AP27: =AN27-AJ27 -> -3.583947 | AQ27: =AO27-AK27 -> -3.583947
G28: 11 | H28: =(utility0/(G28^theta0))^(1/(1-theta0)) -> 11.417666 | I28: =(utility1/(G28^theta1))^(1/(1-theta1)) -> 11.417666 | J28: =(income0/pricez0)-(price0/pricez0)*G28 -> -4.739736 | K28: =(income1/pricez1)-(price1/pricez1)*G28 -> -4.739736 | T28: 11 | U28: =theta0*income0/T28 -> 2.2727273 | V28: =theta1*income1/T28 -> 2.2727273 | W28: =U28*hhno0 -> 227.27273 | X28: =V28*hhno1 -> 227.27273 | AF28: =(beta0*T28*(capital0^(alpha0/beta0))/wage0)^(beta0/(1-beta0)) -> 8.5248179 | AG28: =(beta1*T28*(capital1^(alpha1/beta1))/wage1)^(beta1/(1-beta1)) -> 8.5248179 | AH28: =AF28*firmno0 -> 852.48179 | AI28: =AG28*firmno1 -> 852.48179 | AJ28: =rent0*capital0+wage0*((AF28/(capital0^alpha0))^(1/beta0)) -> 47.509199 | AK28: =rent1*capital1+wage1*((AG28/(capital1^alpha1))^(1/beta1)) -> 47.509199 | AL28: =AJ28/AF28 -> 5.5730456 | AM28: =AK28/AG28 -> 5.5730456 | AN28: =price0*AF28 -> 42.422389 | AO28: =price1*AG28 -> 42.422389 | AP28: =AN28-AJ28 -> -5.0868096 | AQ28: =AO28-AK28 -> -5.0868096
G29: 11.5 | H29: =(utility0/(G29^theta0))^(1/(1-theta0)) -> 10.921245 | I29: =(utility1/(G29^theta1))^(1/(1-theta1)) -> 10.921245 | J29: =(income0/pricez0)-(price0/pricez0)*G29 -> -7.2279058 | K29: =(income1/pricez1)-(price1/pricez1)*G29 -> -7.2279058 | T29: 11.5 | U29: =theta0*income0/T29 -> 2.173913 | V29: =theta1*income1/T29 -> 2.173913 | W29: =U29*hhno0 -> 217.3913 | X29: =V29*hhno1 -> 217.3913 | AF29: =(beta0*T29*(capital0^(alpha0/beta0))/wage0)^(beta0/(1-beta0)) -> 8.7812272 | AG29: =(beta1*T29*(capital1^(alpha1/beta1))/wage1)^(beta1/(1-beta1)) -> 8.7812272 | AH29: =AF29*firmno0 -> 878.12272 | AI29: =AG29*firmno1 -> 878.12272 | AJ29: =rent0*capital0+wage0*((AF29/(capital0^alpha0))^(1/beta0)) -> 50.393645 | AK29: =rent1*capital1+wage1*((AG29/(capital1^alpha1))^(1/beta1)) -> 50.393645 | AL29: =AJ29/AF29 -> 5.738793 | AM29: =AK29/AG29 -> 5.738793 | AN29: =price0*AF29 -> 43.698369 | AO29: =price1*AG29 -> 43.698369 | AP29: =AN29-AJ29 -> -6.6952762 | AQ29: =AO29-AK29 -> -6.6952762
G30: 12 | H30: =(utility0/(G30^theta0))^(1/(1-theta0)) -> 10.466193 | I30: =(utility1/(G30^theta1))^(1/(1-theta1)) -> 10.466193 | J30: =(income0/pricez0)-(price0/pricez0)*G30 -> -9.7160756 | K30: =(income1/pricez1)-(price1/pricez1)*G30 -> -9.7160756 | T30: 12 | U30: =theta0*income0/T30 -> 2.0833333 | V30: =theta1*income1/T30 -> 2.0833333 | W30: =U30*hhno0 -> 208.33333 | X30: =V30*hhno1 -> 208.33333 | AF30: =(beta0*T30*(capital0^(alpha0/beta0))/wage0)^(beta0/(1-beta0)) -> 9.0339459 | AG30: =(beta1*T30*(capital1^(alpha1/beta1))/wage1)^(beta1/(1-beta1)) -> 9.0339459 | AH30: =AF30*firmno0 -> 903.39459 | AI30: =AG30*firmno1 -> 903.39459 | AJ30: =rent0*capital0+wage0*((AF30/(capital0^alpha0))^(1/beta0)) -> 53.36294 | AK30: =rent1*capital1+wage1*((AG30/(capital1^alpha1))^(1/beta1)) -> 53.36294 | AL30: =AJ30/AF30 -> 5.906936 | AM30: =AK30/AG30 -> 5.906936 | AN30: =price0*AF30 -> 44.955983 | AO30: =price1*AG30 -> 44.955983 | AP30: =AN30-AJ30 -> -8.4069573 | AQ30: =AO30-AK30 -> -8.4069573
G31: 12.5 | H31: =(utility0/(G31^theta0))^(1/(1-theta0)) -> 10.047546 | I31: =(utility1/(G31^theta1))^(1/(1-theta1)) -> 10.047546 | J31: =(income0/pricez0)-(price0/pricez0)*G31 -> -12.204245 | K31: =(income1/pricez1)-(price1/pricez1)*G31 -> -12.204245 | T31: 12.5 | U31: =theta0*income0/T31 -> 2 | V31: =theta1*income1/T31 -> 2 | W31: =U31*hhno0 -> 200 | X31: =V31*hhno1 -> 200 | AF31: =(beta0*T31*(capital0^(alpha0/beta0))/wage0)^(beta0/(1-beta0)) -> 9.2831777 | AG31: =(beta1*T31*(capital1^(alpha1/beta1))/wage1)^(beta1/(1-beta1)) -> 9.2831777 | AH31: =AF31*firmno0 -> 928.31777 | AI31: =AG31*firmno1 -> 928.31777 | AJ31: =rent0*capital0+wage0*((AF31/(capital0^alpha0))^(1/beta0)) -> 56.415888 | AK31: =rent1*capital1+wage1*((AG31/(capital1^alpha1))^(1/beta1)) -> 56.415888 | AL31: =AJ31/AF31 -> 6.0772173 | AM31: =AK31/AG31 -> 6.0772173 | AN31: =price0*AF31 -> 46.196245 | AO31: =price1*AG31 -> 46.196245 | AP31: =AN31-AJ31 -> -10.219643 | AQ31: =AO31-AK31 -> -10.219643
... G46: 20 | H46: =(utility0/(G46^theta0))^(1/(1-theta0)) -> 6.2797161 | I46: =(utility1/(G46^theta1))^(1/(1-theta1)) -> 6.2797161 | J46: =(income0/pricez0)-(price0/pricez0)*G46 -> -49.526793 | K46: =(income1/pricez1)-(price1/pricez1)*G46 -> -49.526793 | T46: 20 | U46: =theta0*income0/T46 -> 1.25 | V46: =theta1*income1/T46 -> 1.25 | W46: =U46*hhno0 -> 125 | X46: =V46*hhno1 -> 125 | AF46: =(beta0*T46*(capital0^(alpha0/beta0))/wage0)^(beta0/(1-beta0)) -> 12.699208 | AG46: =(beta1*T46*(capital1^(alpha1/beta1))/wage1)^(beta1/(1-beta1)) -> 12.699208 | AH46: =AF46*firmno0 -> 1269.9208 | AI46: =AG46*firmno1 -> 1269.9208 | AJ46: =rent0*capital0+wage0*((AF46/(capital0^alpha0))^(1/beta0)) -> 111.59367 | AK46: =rent1*capital1+wage1*((AG46/(capital1^alpha1))^(1/beta1)) -> 111.59367 | AL46: =AJ46/AF46 -> 8.7874507 | AM46: =AK46/AG46 -> 8.7874507 | AN46: =price0*AF46 -> 63.195574 | AO46: =price1*AG46 -> 63.195574 | AP46: =AN46-AJ46 -> -48.398093 | AQ46: =AO46-AK46 -> -48.398093

Sheet Keterangan

Sheet Diagram
M4: Awal | O4: Akhir
J5: Parameter utility | L5: q | M5: 0.5 | O5: =Q5/100 -> 0.5 | Q5: 50
J6: Pendapatan | L6: y | M6: 50 | O6: =Q6 -> 50 | Q6: 50
J7: Jumlah konsumen | L7: H | M7: 100 | O7: =Q7 -> 100 | Q7: 100
J8: Upah | L8: w | M8: 0.5 | O8: =Q8/100 -> 0.5 | Q8: 50
J9: Parameter produksi | L9: α | M9: 0.6 | O9: =Q9/100 -> 0.6 | Q9: 60
L10: β | M10: 0.4 | O10: =Q10/100 -> 0.4 | Q10: 40
J11: Kapital | L11: K | M11: 2 | O11: =Q11/10 -> 2 | Q11: 20
J12: Sewa kapital | L12: r | M12: 5 | O12: =Q12/10 -> 5 | Q12: 50
J13: Jumlah produsen | L13: N | M13: 100 | O13: =Q13 -> 100 | Q13: 100
